dynmix
