Metadata-Version: 2.1
Name: dynmix
Version: 1.0.0
Summary: Dynamix Membership Mixture Models
Home-page: https://github.com/vsartor/dynmix
Author: Victhor S. Sartório
Author-email: victhor@dme.ufrj.br
License: UNKNOWN
Keywords: mixture model bayesian statistics dynamic
Platform: UNKNOWN
Classifier: Development Status :: 1 - Planning
Classifier: Intended Audience :: Science/Research
Classifier: Topic :: Scientific/Engineering :: Information Analysis
Classifier: License :: OSI Approved :: MIT License
Classifier: Programming Language :: Python :: 3
Classifier: Programming Language :: Python :: 3.7
